{"aditional": 0, "success": true, "data": {"lCargoElecHistorico": [{"strUsuario": null, "strEstado": "ACTIVO (U)", "strCargoEleccion": "PRESIDENTE DE LA REP\u00daBLICA", "idEstado": 2, "idCargoEleccion": 1}, {"strUsuario": null, "strEstado": "ACTIVO (U)", "strCargoEleccion": "PRIMER VICEPRESIDENTE DE LA REP\u00daBLICA", "idEstado": 2, "idCargoEleccion": 2}, {"strUsuario": null, "strEstado": "ACTIVO (U)", "strCargoEleccion": "SEGUNDO VICEPRESIDENTE DE LA REP\u00daBLICA", "idEstado": 2, "idCargoEleccion": 3}, {"strUsuario": null, "strEstado": "ACTIVO (U)", "strCargoEleccion": "CONGRESISTA DE LA REP\u00daBLICA", "idEstado": 2, "idCargoEleccion": 4}, {"strUsuario": null, "strEstado": "ACTIVO (U)", "strCargoEleccion": "REPRESENTANTE ANTE EL PARLAMENTO ANDINO", "idEstado": 2, "idCargoEleccion": 5}, {"strUsuario": null, "strEstado": "ACTIVO (U)", "strCargoEleccion": "GOBERNADOR REGIONAL", "idEstado": 2, "idCargoEleccion": 6}, {"strUsuario": null, "strEstado": "ACTIVO (U)", "strCargoEleccion": "VICEGOBERNADOR REGIONAL", "idEstado": 2, "idCargoEleccion": 7}, {"strUsuario": null, "strEstado": "ACTIVO (U)", "strCargoEleccion": "ALCALDE PROVINCIAL", "idEstado": 2, "idCargoEleccion": 8}, {"strUsuario": null, "strEstado": "ACTIVO (U)", "strCargoEleccion": "REGIDOR PROVINCIAL", "idEstado": 2, "idCargoEleccion": 9}, {"strUsuario": null, "strEstado": "ACTIVO (U)", "strCargoEleccion": "ALCALDE DISTRITAL", "idEstado": 2, "idCargoEleccion": 10}, {"strUsuario": null, "strEstado": "ACTIVO (U)", "strCargoEleccion": "REGIDOR DISTRITAL", "idEstado": 2, "idCargoEleccion": 11}, {"strUsuario": null, "strEstado": "ACTIVO (U)", "strCargoEleccion": "CONSEJERO REGIONAL", "idEstado": 2, "idCargoEleccion": 12}, {"strUsuario": null, "strEstado": "ACTIVO (U)", "strCargoEleccion": "ACCESITARIO", "idEstado": 2, "idCargoEleccion": 13}, {"strUsuario": null, "strEstado": "ACTIVO (R)", "strCargoEleccion": "REGIDOR DE CENTRO POBLADO", "idEstado": 1, "idCargoEleccion": 14}, {"strUsuario": null, "strEstado": "ACTIVO (R)", "strCargoEleccion": "DIPUTADO", "idEstado": 1, "idCargoEleccion": 15}, {"strUsuario": null, "strEstado": "ACTIVO (R)", "strCargoEleccion": "SENADOR", "idEstado": 1, "idCargoEleccion": 16}, {"strUsuario": null, "strEstado": "ACTIVO (R)", "strCargoEleccion": "ALCADE(SA) DE CENTRO POBLADO", "idEstado": 1, "idCargoEleccion": 17}, {"strUsuario": null, "strEstado": "ACTIVO (R)", "strCargoEleccion": "CONGRESISTA CONSTITUYENTE", "idEstado": 1, "idCargoEleccion": 18}, {"strUsuario": null, "strEstado": "ACTIVO (R)", "strCargoEleccion": "REGIDOR PROVINCIAL SUPLENTE", "idEstado": 1, "idCargoEleccion": 19}, {"strUsuario": null, "strEstado": "ACTIVO (R)", "strCargoEleccion": "REPRESENTANTE DE ASAMBLEA REGIONAL", "idEstado": 1, "idCargoEleccion": 20}, {"strUsuario": null, "strEstado": "ACTIVO (R)", "strCargoEleccion": "REGIDOR DISTRITAL SUPLENTE", "idEstado": 1, "idCargoEleccion": 21}], "lExperienciaLaboral": [{"strTrabajoUbiProvincia": null, "strTrabajoDepartamento": "PIURA", "strCentroTrabajo": "MUNICIPALIDAD DISTRITAL DE MARCAVELICA", "strTrabajoProvincia": "SULLANA", "strDireccionTrabajo": "PLAZA MIGUEL GRAU SN", "strTrabajoUbiDepartamento": null, "strRucTrabajo": "", "strAnioTrabajoDesde": "2020", "intItemExpeLaboral": 1, "strTengoExpeLaboral": "1", "idEstado": 1, "strTrabajoUbiDistrito": null, "strTrabajoDistrito": "MARCAVELICA", "strOrder": null, "strOcupacionProfesion": "ASESOR ADMINISTRATIVO - GESTOR EN EJECUCION DE  INVERSIONES", "strUbigeoTrabajo": "190604", "strUsuario": "15354852", "idHVExpeLaboral": 149962, "strAnioTrabajoHasta": "0000", "idHojaVida": 133969, "strTrabajoPais": "PER\u00da"}, {"strTrabajoUbiProvincia": null, "strTrabajoDepartamento": "PIURA", "strCentroTrabajo": "MUNICIPALIDAD DISTRITAL DE MARCAVELICA", "strTrabajoProvincia": "SULLANA", "strDireccionTrabajo": "PLAZA MIGUEL GRAU SN", "strTrabajoUbiDepartamento": null, "strRucTrabajo": "", "strAnioTrabajoDesde": "2019", "intItemExpeLaboral": 2, "strTengoExpeLaboral": "1", "idEstado": 1, "strTrabajoUbiDistrito": null, "strTrabajoDistrito": "MARCAVELICA", "strOrder": null, "strOcupacionProfesion": "ASESOR ADMINISTRATIVO EXTERNO", "strUbigeoTrabajo": "190604", "strUsuario": "15354852", "idHVExpeLaboral": 149963, "strAnioTrabajoHasta": "2019", "idHojaVida": 133969, "strTrabajoPais": "PER\u00da"}, {"strTrabajoUbiProvincia": null, "strTrabajoDepartamento": "PIURA", "strCentroTrabajo": "MUNICIPALIDAD DISTRITAL DE QUERECOTILLO", "strTrabajoProvincia": "SULLANA", "strDireccionTrabajo": "CALLE GRAU 112", "strTrabajoUbiDepartamento": null, "strRucTrabajo": "", "strAnioTrabajoDesde": "2017", "intItemExpeLaboral": 3, "strTengoExpeLaboral": "1", "idEstado": 1, "strTrabajoUbiDistrito": null, "strTrabajoDistrito": "QUERECOTILLO", "strOrder": null, "strOcupacionProfesion": "GERENTE MUNICIPAL", "strUbigeoTrabajo": "190606", "strUsuario": "15354852", "idHVExpeLaboral": 149964, "strAnioTrabajoHasta": "2018", "idHojaVida": 133969, "strTrabajoPais": "PER\u00da"}, {"strTrabajoUbiProvincia": null, "strTrabajoDepartamento": "PIURA", "strCentroTrabajo": "GERENCIA SUB REGIONAL LUCIANO CASTILLO COLONNA-GOBIERNO REGIONAL DE PIURA", "strTrabajoProvincia": "SULLANA", "strDireccionTrabajo": "CARRTERA SULLANA-TAMBOGRANDE", "strTrabajoUbiDepartamento": null, "strRucTrabajo": "", "strAnioTrabajoDesde": "2015", "intItemExpeLaboral": 4, "strTengoExpeLaboral": "1", "idEstado": 1, "strTrabajoUbiDistrito": null, "strTrabajoDistrito": "SULLANA", "strOrder": null, "strOcupacionProfesion": "JEFE DE OFICINA SUB REGIONAL  DE ADMINISTRACION", "strUbigeoTrabajo": "190601", "strUsuario": "15354852", "idHVExpeLaboral": 149968, "strAnioTrabajoHasta": "2016", "idHojaVida": 133969, "strTrabajoPais": "PER\u00da"}, {"strTrabajoUbiProvincia": null, "strTrabajoDepartamento": "PIURA", "strCentroTrabajo": "MUNICIPALIDAD DISTRITAL DE QUERECOTILLO", "strTrabajoProvincia": "SULLANA", "strDireccionTrabajo": "CALLE GRAU 112", "strTrabajoUbiDepartamento": null, "strRucTrabajo": "", "strAnioTrabajoDesde": "2011", "intItemExpeLaboral": 5, "strTengoExpeLaboral": "1", "idEstado": 1, "strTrabajoUbiDistrito": null, "strTrabajoDistrito": "QUERECOTILLO", "strOrder": null, "strOcupacionProfesion": "GERENTE MUNICIPAL", "strUbigeoTrabajo": "190606", "strUsuario": "15354852", "idHVExpeLaboral": 149969, "strAnioTrabajoHasta": "2014", "idHojaVida": 133969, "strTrabajoPais": "PER\u00da"}], "lCargoEleccion": [{"strUsuario": null, "strAnioCargoElecHasta": "", "strComentario": "", "strCargoEleccion": "2", "idEstado": 1, "idCargoEleccion": 0, "idHojaVida": 133969, "strAnioCargoElecDesde": "", "strCargoEleccion2": "", "strOrder": null, "idHVCargoEleccion": 132026, "idOrgPolCargoElec": 0, "strOrgPolCargoElec": "", "intItemCargoEleccion": 1}], "lBienMuebleOtro": [], "lBienInmueble": [{"strInmuebleUbiDistrito": null, "strInmuebleProvincia": "", "strTengoInmueble": "2", "strComentario": "", "intItemInmueble": 1, "strInmuebleUbiProvincia": null, "strInmuebleDireccion": "", "strInmuebleUbiDepartamento": null, "strInmuebleDepartamento": "", "strFichaTomoSunarp": "", "strInmuebleSunarp": "", "strInmuebleDistrito": "", "strInmueblePais": "", "idHojaVida": 133969, "decAutovaluo": 0, "strPartidaSunarp": "", "strUsuario": "15354852", "decUIT": 0, "idEstado": 1, "idHVBienInmueble": 162093, "strOrder": null, "strTipoBienInmueble": "", "strUbigeoInmueble": ""}], "lEduUniversitaria": [{"idEstado": 1, "strUsuario": null, "strAnioTitulo": "", "strBachillerEduUni": "", "strEduUniversitaria": "1", "strComentario": "", "strOrder": null, "strTengoEduUniversitaria": "1", "strAnioBachiller": "2019", "intItemEduUni": 1, "strTituloUni": "", "strUniversidad": "UNIVERSIDAD SAN PEDRO", "strEgresadoEduUni": "1", "strMetodoAccion": null, "strCarreraUni": "BACHILLER EN INGENIERIA CIVIL", "idHojaVida": 0, "idHVEduUniversitaria": 136719, "strConcluidoEduUni": "1"}], "lSentenciaObliga": [{"strTengoSentenciaObliga": "1", "strOrganoJuridicialObliga": "8VO JUZGADO PAZ LETRADO CIVIL", "idHVSentenciaObliga": 130433, "strUsuario": null, "idParamMateriaSentencia": 17, "strExpedienteObliga": "02494-2017-0-2001-JP-CI-04", "idEstado": 1, "intItemSentenciaObliga": 1, "idHojaVida": 133969, "strEstado": null, "strOrder": null, "strFalloObliga": "FUNDADA", "strMateriaSentencia": "CONTRACTUAL"}], "oEduTecnico": {"strUsuario": null, "idHVEduTecnico": 130652, "strComentario": "EGRESADO SIN TITULO", "strCenEstudioTecnico": "INSTITUTO SUPERIOIR TECNOLOGO JUAN JOSE FARFAN CESPEDES", "idEstado": 1, "idHojaVida": 133969, "strCarreraTecnico": "ADMINISTRACION", "strTengoEduTecnico": "1", "strConcluidoEduTecnico": "1"}, "oEduBasica": {"strUsuario": null, "strConcluidoEduPrimaria": "1", "strTengoEduBasica": "1", "idEstado": 1, "idHojaVida": 133969, "strEduSecundaria": "1", "idHVEduBasica": 133202, "strEduPrimaria": "1", "strConcluidoEduSecundaria": "1"}, "lCargoPartidario": [{"strCargoPartidario": "", "strUsuario": null, "strAnioCargoPartiHasta": "", "idHVCargoPartidario": 131636, "strAnioCargoPartiDesde": "", "strComentario": "", "idEstado": 1, "strTengoCargoPartidario": "2", "idHojaVida": 133969, "idOrgPolCargoPartidario": 0, "strOrder": null, "intItemCargoPartidario": 1, "strOrgPolCargoPartidario": ""}], "oIngresos": {"strUsuario": null, "strTengoIngresos": "1", "idHVIngresos": 132559, "strAnioIngresos": "2019", "decOtroIngresoPublico": 0, "decOtroIngresoPrivado": 0, "decRentaIndividualPrivado": 0, "idEstado": 1, "idHojaVida": 133969, "decRemuBrutaPublico": 0, "decRemuBrutaPrivado": 0, "decRentaIndividualPublico": 35000}, "lCargoElecPostula": [{"strUsuario": null, "strEstado": "ACTIVO (U)", "strCargoEleccion": "PRESIDENTE DE LA REP\u00daBLICA", "idEstado": 2, "idCargoEleccion": 1}, {"strUsuario": null, "strEstado": "ACTIVO (U)", "strCargoEleccion": "PRIMER VICEPRESIDENTE DE LA REP\u00daBLICA", "idEstado": 2, "idCargoEleccion": 2}, {"strUsuario": null, "strEstado": "ACTIVO (U)", "strCargoEleccion": "SEGUNDO VICEPRESIDENTE DE LA REP\u00daBLICA", "idEstado": 2, "idCargoEleccion": 3}, {"strUsuario": null, "strEstado": "ACTIVO (U)", "strCargoEleccion": "CONGRESISTA DE LA REP\u00daBLICA", "idEstado": 2, "idCargoEleccion": 4}, {"strUsuario": null, "strEstado": "ACTIVO (U)", "strCargoEleccion": "REPRESENTANTE ANTE EL PARLAMENTO ANDINO", "idEstado": 2, "idCargoEleccion": 5}, {"strUsuario": null, "strEstado": "ACTIVO (U)", "strCargoEleccion": "GOBERNADOR REGIONAL", "idEstado": 2, "idCargoEleccion": 6}, {"strUsuario": null, "strEstado": "ACTIVO (U)", "strCargoEleccion": "VICEGOBERNADOR REGIONAL", "idEstado": 2, "idCargoEleccion": 7}, {"strUsuario": null, "strEstado": "ACTIVO (U)", "strCargoEleccion": "ALCALDE PROVINCIAL", "idEstado": 2, "idCargoEleccion": 8}, {"strUsuario": null, "strEstado": "ACTIVO (U)", "strCargoEleccion": "REGIDOR PROVINCIAL", "idEstado": 2, "idCargoEleccion": 9}, {"strUsuario": null, "strEstado": "ACTIVO (U)", "strCargoEleccion": "ALCALDE DISTRITAL", "idEstado": 2, "idCargoEleccion": 10}, {"strUsuario": null, "strEstado": "ACTIVO (U)", "strCargoEleccion": "REGIDOR DISTRITAL", "idEstado": 2, "idCargoEleccion": 11}, {"strUsuario": null, "strEstado": "ACTIVO (U)", "strCargoEleccion": "CONSEJERO REGIONAL", "idEstado": 2, "idCargoEleccion": 12}, {"strUsuario": null, "strEstado": "ACTIVO (U)", "strCargoEleccion": "ACCESITARIO", "idEstado": 2, "idCargoEleccion": 13}, {"strUsuario": null, "strEstado": "ACTIVO (R)", "strCargoEleccion": "REGIDOR DE CENTRO POBLADO", "idEstado": 1, "idCargoEleccion": 14}, {"strUsuario": null, "strEstado": "ACTIVO (R)", "strCargoEleccion": "ALCADE(SA) DE CENTRO POBLADO", "idEstado": 1, "idCargoEleccion": 17}], "oEduPosgrago": {"strUsuario": null, "strEgresadoPosgrado": "0", "idHVPosgrado": 130440, "strEsDoctor": "0", "strAnioPosgrado": "", "strComentario": "EN CURSO TERCER SEMESTRE", "strEspecialidadPosgrado": "MAESTRIA EN DIRECCION DE PROYECTOS", "idEstado": 1, "strTengoPosgrado": "1", "strEsMaestro": "0", "intItemPosgrado": 1, "strCenEstudioPosgrado": "UNIVERSIDAD  DE PIURA", "idHojaVida": 133969, "strConcluidoPosgrado": "2"}, "lAnotacionMarginal": [], "oInfoAdicional": {"strUsuario": null, "strInfoAdicional": "INGENIERO INDUSTRIAL DE LA UNIVERSIDAD NACIONAL DE PIURA, CONCLUIDO, OBTENCION A\u00d1O 2000\n/PERTENECIO AL MOVIIENTO REGIONAL DE DESARROLLO LOCAL  PIURA 2005 -2011 ORGANIZACION CANCELADA\n/ TRABAJO DEL 02-01-2020 HASTA EL 30-06-2020 EN EL CARGO DE ASESOR ADM. EXTERNO Y DEL 01-07-2020 HASTA LA  ACTUALIDAD COMO GESTOR EN EJECUCION DE INVERSION EN LA MUNICIPALIDAD DISTRITAL DE MARCAVELICA/ EN CUANTO AL TRABAJO ACTUAL COMO ASESOR ADMINITSRATIVO-GESTOR EN EJECUCCION DE INVERSIONES EN LA MUNICIPALIDAD DISTRITAL DE MARCAVELICA NO SE SOLICITA LICENCIA, YA QUE EL CONTRATO LABORAL ES HASTA EL 31/12/2020 EL CUAL NO SERA RENOVADO.", "idEstado": 1, "idHVInfoAdicional": 130080, "idHojaVida": 133969, "strTengoInfoAdicional": "1"}, "lRenunciaOP": [{"strTengoRenunciaOP": "2", "strUsuario": "15354852", "idOrgPolRenunciaOP": 0, "strComentario": "", "strOrder": null, "cadenaRenuncia": null, "idEstado": 1, "idHojaVida": 133969, "strFechaRegistro": "10/12/2020 11:28:17 a.m.", "intItemRenunciaOP": 1, "idHVRenunciaOP": 131562, "strOrgPolRenunciaOP": "", "strAnioRenunciaOP": ""}], "lBienMueble": [{"strUsuario": null, "strTengoBienMueble": "1", "strMarca": "", "strPlaca": "NB67491", "strVehiculo": "MOTOCICLETA", "intItemMueble": 1, "strComentario": "", "idEstado": 1, "strCaracteristica": "REPPA ROJO", "idHojaVida": 133969, "decValor": 1200, "strOrder": null, "strAnio": "", "strModelo": "", "idHVBienMueble": 143331}, {"strUsuario": null, "strTengoBienMueble": "1", "strMarca": "", "strPlaca": "NB67492", "strVehiculo": "MOTOCICLETA", "intItemMueble": 2, "strComentario": "", "idEstado": 1, "strCaracteristica": "REPPA MOD. RA 150 GY3", "idHojaVida": 133969, "decValor": 1200, "strOrder": null, "strAnio": "", "strModelo": "", "idHVBienMueble": 143335}, {"strUsuario": null, "strTengoBienMueble": "1", "strMarca": "", "strPlaca": "P11090", "strVehiculo": "MOTOCICLETA", "intItemMueble": 3, "strComentario": "", "idEstado": 1, "strCaracteristica": "REPPA MOD. RP150", "idHojaVida": 133969, "decValor": 1500, "strOrder": null, "strAnio": "", "strModelo": "", "idHVBienMueble": 143337}], "oDatosPersonales": {"strDomiUbiDistrito": null, "idCandidato": 165050, "strEnlaceMenu": null, "idProcesoElectoral": 110, "idCargoEleccion": 4, "strApellidoMaterno": "ATOCHE", "idParamHojaVida": 25, "strUbigeoNacimiento": "190601", "strUbigeoDomicilio": "190601", "strSexo": "1", "strDomiProvincia": "SULLANA", "strDomiDistrito": "SULLANA", "strUbigeoPostula": "190000", "strNombres": "CESAR AUGUSTO", "strHojaVida": "CONFIRMADO", "strRegistro": null, "strDocumentoIdentidad": "03651264", "intCantidadReg": 0, "strPostulaUbiProvincia": null, "strDomiDepartamento": "PIURA", "strClase": null, "intCantidadPagina": 0, "strDomicilioDirecc": "AV.BUENOS AIRES 503 ASENT.H.9 DE OCTUBRE", "idCandidatoOtro": 0, "strCarneExtranjeria": "", "idOrganizacionPolitica": 0, "strDomiUbiDepartamento": null, "strterminoregistro": null, "strPaisNacimiento": "PER\u00da", "strProcesoElectoral": 0, "idHojaVida": 133969, "strNaciDistrito": "SULLANA", "strNaciUbiDistrito": null, "strNaciProvincia": "SULLANA", "strDomiUbiProvincia": null, "idCargoEleccionOtro": 0, "strPostulaUbiDistrito": null, "strFechaNacimiento": "20/04/1967", "strPostulaUbiDepartamento": null, "strApellidoPaterno": "CORREA", "strUsuario": "15354852", "strPostulaDistrito": "PIURA", "idUsuario": 0, "strPostulaProvincia": " ", "decPorcentaje": 100, "intItem": 0, "strNaciUbiProvincia": null, "strCargoEleccion": null, "idEstado": 2, "strFeTerminoRegistro": "11/12/2020 09:20:00", "intPagina": 0, "strEstado": "ACTIVO (U)", "strRutaArchivo": "/Assets/Fotos-HojaVida/133969.jpg", "idTipoEleccion": 0, "strNaciUbiDepartamento": null, "strPostulaDepartamento": " ", "strNombreArchivo": "", "strAnioPostula": "2020", "strNaciDepartamento": "PIURA"}, "lSentenciaPenal": [{"strUsuario": null, "strDelitoPenal": "", "strModalidad": "", "idHVSentenciaPenal": 130274, "strTengoSentenciaPenal": "2", "intItemSentenciaPenal": 1, "strFechaSentenciaPenal": "", "idEstado": 1, "strExpedientePenal": "", "idHojaVida": 133969, "idParamCumpleFallo": 0, "strOrder": null, "idParamModalidad": 0, "strFalloPenal": "", "strCumpleFallo": "", "strOtraModalidad": "", "strOrganoJudiPenal": ""}], "oEduNoUniversitaria": {"strCarreraNoUni": "", "strEduNoUniversitaria": "2", "strUsuario": null, "strConcluidoNoUni": "0", "idEstado": 1, "strCentroEstudioNoUni": "", "strTengoNoUniversitaria": "1", "idHVNoUniversitaria": 131374, "idHojaVida": 133969}}, "extravalue": null, "messageLog": "", "message": "", "type": 1}